pltnump.py
pltnump-0.1.0.dist-info/METADATA
pltnump-0.1.0.dist-info/WHEEL
pltnump-0.1.0.dist-info/RECORD
