Metadata-Version: 2.1
Name: pltnump
Version: 0.1.0
Summary: 
Author: alex_past
Requires-Python: >=3.11,<4.0
Classifier: Programming Language :: Python :: 3
Classifier: Programming Language :: Python :: 3.11
Classifier: Programming Language :: Python :: 3.12
